bme280/__init__.py
bme280/bme280.py
bme280/bme280_i2c.py
bme280-0.5.dist-info/DESCRIPTION.rst
bme280-0.5.dist-info/METADATA
bme280-0.5.dist-info/RECORD
bme280-0.5.dist-info/WHEEL
bme280-0.5.dist-info/entry_points.txt
bme280-0.5.dist-info/metadata.json
bme280-0.5.dist-info/top_level.txt
